{"data":[{"id":561965846,"type":"answer","answer_type":"normal","question":{"type":"question","id":306537777,"title":"如果高中生能证明哥德巴赫猜想，会被清华北大数学系保送吗？","question_type":"normal","created":1545408745,"updated_time":1545408745,"url":"https://www.zhihu.com/api/v4/questions/306537777","relationship":{}},"author":{"id":"b85a9231c4ef54972c2494ff9dfcc576","url_token":"zhang-david-24","name":"创国大国师","avatar_url":"https://pic1.zhimg.com/5492b18af851d8c307bccb21b112dadc_is.jpg","avatar_url_template":"https://pic1.zhimg.com/5492b18af851d8c307bccb21b112dadc_{size}.jpg","is_org":false,"type":"people","url":"https://www.zhihu.com/api/v4/people/b85a9231c4ef54972c2494ff9dfcc576","user_type":"people","headline":"","badge":[],"gender":1,"is_advertiser":false,"is_privacy":false},"url":"https://www.zhihu.com/api/v4/answers/561965846","thumbnail":"https://pic1.zhimg.com/v2-ce99a88a842df8ffc55080ee08b5be5e_200x112.jpg","is_collapsed":false,"created_time":1546027340,"updated_time":1546027350,"extras":"","is_copyable":true,"is_normal":true,"voteup_count":0,"content":"\u003cp\u003e一个数学水平高的人，一个热爱数学，并真心想要钻研数学的人，是不会一上来好高骛远的，也不会用这种事情作为炒作自己的方式。请恕我直言，你不是爱好数学，只是想要用数学炒作自己罢了。对于你这种人，我只有一张图送你了。\u003c/p\u003e\u003cfigure\u003e\u003cnoscript\u003e\u003cimg src=\"https://pic3.zhimg.com/v2-ce99a88a842df8ffc55080ee08b5be5e_b.jpg\" data-rawwidth=\"630\" data-rawheight=\"587\" data-size=\"normal\" class=\"origin_image zh-lightbox-thumb\" width=\"630\" data-original=\"https://pic3.zhimg.com/v2-ce99a88a842df8ffc55080ee08b5be5e_r.jpg\"\u003e\u003c/noscript\u003e\u003cimg src=\"data:image/svg+xml;utf8,\u0026lt;svg%20xmlns='http://www.w3.org/2000/svg'%20width='630'%20height='587'\u0026gt;\u0026lt;/svg\u0026gt;\" data-rawwidth=\"630\" data-rawheight=\"587\" data-size=\"normal\" class=\"origin_image zh-lightbox-thumb lazy\" width=\"630\" data-original=\"https://pic3.zhimg.com/v2-ce99a88a842df8ffc55080ee08b5be5e_r.jpg\" data-actualsrc=\"https://pic3.zhimg.com/v2-ce99a88a842df8ffc55080ee08b5be5e_b.jpg\"\u003e\u003c/figure\u003e\u003cp\u003e\u003c/p\u003e","relationship":{"upvoted_followees":[]}},{"id":561960041,"type":"answer","answer_type":"normal","question":{"type":"question","id":306537777,"title":"如果高中生能证明哥德巴赫猜想，会被清华北大数学系保送吗？","question_type":"normal","created":1545408745,"updated_time":1545408745,"url":"https://www.zhihu.com/api/v4/questions/306537777","relationship":{}},"author":{"id":"5e2fa9169b7ebeaed9636a351b0781e8","url_token":"qia-mi-sa-ma-28","name":"卡密撒嘛","avatar_url":"https://pic4.zhimg.com/v2-9073da936074e758982a77dbb194b7f6_is.jpg","avatar_url_template":"https://pic4.zhimg.com/v2-9073da936074e758982a77dbb194b7f6_{size}.jpg","is_org":false,"type":"people","url":"https://www.zhihu.com/api/v4/people/5e2fa9169b7ebeaed9636a351b0781e8","user_type":"people","headline":"理性客观","badge":[],"gender":-1,"is_advertiser":false,"is_privacy":false},"url":"https://www.zhihu.com/api/v4/answers/561960041","thumbnail":"","is_collapsed":false,"created_time":1546023723,"updated_time":1546023919,"extras":"","is_copyable":true,"is_normal":true,"voteup_count":0,"content":"\u003cp\u003e彻头彻尾的钓鱼问题。\u003c/p\u003e\u003cp\u003e几个月前还在看高中数学相关知识的人说突然解决了世界性难题，那可不是啥天才了，那要么得上帝给你附身了，要么就是你回想起你前世就是上帝并继承了所有记忆。\u003c/p\u003e\u003cp\u003e下面这么多回答都告诉了你哥猜是什么级别的问题，甚至连相关的证明都贴了出来。一个几个月前还在关注隐函数这种问题的高中生却说要证明，要真给你证明出来，数学这种学科还有存在的必要？\u003c/p\u003e\u003cp\u003e脚踏实地好好学习吧。。。当然你已经成功了，20k的关注，超多的流量，相信你未来会过得顺风顺水。但针对这个问题，如果你是认真的，只能说你蚍蜉撼大树，可笑不自量。\u003c/p\u003e","relationship":{"upvoted_followees":[]}},{"id":561953764,"type":"answer","answer_type":"normal","question":{"type":"question","id":306537777,"title":"如果高中生能证明哥德巴赫猜想，会被清华北大数学系保送吗？","question_type":"normal","created":1545408745,"updated_time":1545408745,"url":"https://www.zhihu.com/api/v4/questions/306537777","relationship":{}},"author":{"id":"b653df5d49ab3839be700f62c79d8b4b","url_token":"zhi-ke-suan-fa","name":"智客算法","avatar_url":"https://pic4.zhimg.com/b64a9109fd244c5263b29ac2a0897af6_is.jpg","avatar_url_template":"https://pic4.zhimg.com/b64a9109fd244c5263b29ac2a0897af6_{size}.jpg","is_org":false,"type":"people","url":"https://www.zhihu.com/api/v4/people/b653df5d49ab3839be700f62c79d8b4b","user_type":"people","headline":"在线的前沿爬虫","badge":[],"gender":-1,"is_advertiser":false,"is_privacy":false},"url":"https://www.zhihu.com/api/v4/answers/561953764","thumbnail":"","is_collapsed":false,"created_time":1546021179,"updated_time":1546021214,"extras":"","is_copyable":true,"is_normal":true,"voteup_count":0,"content":"\u003cp\u003e高中以前的数学就是过家家，多做点题，理清思路正常考个子95%没有问题。\u003c/p\u003e\u003cp\u003e只是证明哥德巴赫猜想的人，他数学天资一定足以证明他不玩知乎。因为要够的上入门资格，挤出逛知乎的时间来也远远不够。希望题主将来不要因为高数而头疼。\u003c/p\u003e","relationship":{"upvoted_followees":[]}},{"id":561952964,"type":"answer","answer_type":"normal","question":{"type":"question","id":306537777,"title":"如果高中生能证明哥德巴赫猜想，会被清华北大数学系保送吗？","question_type":"normal","created":1545408745,"updated_time":1545408745,"url":"https://www.zhihu.com/api/v4/questions/306537777","relationship":{}},"author":{"id":"9d05a4e5238203ea763b6935239f224e","url_token":"lisxiao-gong-ju","name":"阿诺德丶帅","avatar_url":"https://pic2.zhimg.com/v2-fa3395636a87d07b4f631e794523e7f9_is.jpg","avatar_url_template":"https://pic2.zhimg.com/v2-fa3395636a87d07b4f631e794523e7f9_{size}.jpg","is_org":false,"type":"people","url":"https://www.zhihu.com/api/v4/people/9d05a4e5238203ea763b6935239f224e","user_type":"people","headline":"往事随风  一走八千里","badge":[],"gender":-1,"is_advertiser":false,"is_privacy":false},"url":"https://www.zhihu.com/api/v4/answers/561952964","thumbnail":"","is_collapsed":false,"created_time":1546020938,"updated_time":1546020960,"extras":"","is_copyable":true,"is_normal":true,"voteup_count":0,"content":"\u003cp\u003e德布罗意毕业论文就可以得诺贝尔物理学奖\u003c/p\u003e\u003cp\u003e你当然可以用菲尔兹奖换个清北录取通知书\u003c/p\u003e","relationship":{"upvoted_followees":[]}},{"id":561949218,"type":"answer","answer_type":"normal","question":{"type":"question","id":306537777,"title":"如果高中生能证明哥德巴赫猜想，会被清华北大数学系保送吗？","question_type":"normal","created":1545408745,"updated_time":1545408745,"url":"https://www.zhihu.com/api/v4/questions/306537777","relationship":{}},"author":{"id":"cf9c2516c0c5d8116aa53d54194e0761","url_token":"xun-wu-zhao","name":"Justin 天","avatar_url":"https://pic2.zhimg.com/v2-609065c881b43c1cc341aaa1394dba99_is.jpg","avatar_url_template":"https://pic2.zhimg.com/v2-609065c881b43c1cc341aaa1394dba99_{size}.jpg","is_org":false,"type":"people","url":"https://www.zhihu.com/api/v4/people/cf9c2516c0c5d8116aa53d54194e0761","user_type":"people","headline":"高中生","badge":[],"gender":-1,"is_advertiser":false,"is_privacy":false},"url":"https://www.zhihu.com/api/v4/answers/561949218","thumbnail":"https://pic4.zhimg.com/v2-962ae1690bbd32258bc2ce0047ea81c2_200x112.jpg","is_collapsed":false,"created_time":1546019709,"updated_time":1546019715,"extras":"","is_copyable":true,"is_normal":true,"voteup_count":0,"content":"\u003cp\u003e我已经找到一个证明哥德巴赫猜想的精妙方法，而这个页面没有足够的空位写下。\u003c/p\u003e\u003cfigure\u003e\u003cnoscript\u003e\u003cimg src=\"https://pic3.zhimg.com/v2-bb834f7beeba04bfb40b2d18a5c2dd46_b.jpg\" data-rawwidth=\"250\" data-rawheight=\"250\" data-size=\"normal\" data-default-watermark-src=\"https://pic4.zhimg.com/v2-2afeaf64c0a9be7a201c7e21bfe5266b_b.jpg\" class=\"content_image\" width=\"250\"\u003e\u003c/noscript\u003e\u003cimg src=\"data:image/svg+xml;utf8,\u0026lt;svg%20xmlns='http://www.w3.org/2000/svg'%20width='250'%20height='250'\u0026gt;\u0026lt;/svg\u0026gt;\" data-rawwidth=\"250\" data-rawheight=\"250\" data-size=\"normal\" data-default-watermark-src=\"https://pic4.zhimg.com/v2-2afeaf64c0a9be7a201c7e21bfe5266b_b.jpg\" class=\"content_image lazy\" width=\"250\" data-actualsrc=\"https://pic3.zhimg.com/v2-bb834f7beeba04bfb40b2d18a5c2dd46_b.jpg\"\u003e\u003c/figure\u003e\u003cp\u003e\u003c/p\u003e","relationship":{"upvoted_followees":[]}},{"id":561938849,"type":"answer","answer_type":"normal","question":{"type":"question","id":306537777,"title":"如果高中生能证明哥德巴赫猜想，会被清华北大数学系保送吗？","question_type":"normal","created":1545408745,"updated_time":1545408745,"url":"https://www.zhihu.com/api/v4/questions/306537777","relationship":{}},"author":{"id":"522b0144169087002edddf125805f17a","url_token":"","name":"知乎用户","avatar_url":"https://pic4.zhimg.com/da8e974dc_is.jpg","avatar_url_template":"https://pic4.zhimg.com/da8e974dc_{size}.jpg","is_org":false,"type":"people","url":"https://www.zhihu.com/api/v4/people/0","user_type":"people","headline":"","badge":[],"gender":1,"is_advertiser":false,"is_privacy":true},"url":"https://www.zhihu.com/api/v4/answers/561938849","thumbnail":"https://pic4.zhimg.com/v2-316d6830b8058e83003294961ad4528e_200x112.jpg","is_collapsed":false,"created_time":1546017397,"updated_time":1546017404,"extras":"","is_copyable":true,"is_normal":true,"voteup_count":0,"content":"\u003cp\u003e不能。理由如下\u003c/p\u003e\u003cfigure\u003e\u003cnoscript\u003e\u003cimg src=\"https://pic3.zhimg.com/v2-9b8fb5e5230b83e9e47aa0c74311bf06_b.jpg\" data-caption=\"\" data-size=\"normal\" data-rawwidth=\"824\" data-rawheight=\"447\" data-default-watermark-src=\"https://pic3.zhimg.com/v2-9b8fb5e5230b83e9e47aa0c74311bf06_b.jpg\" class=\"origin_image zh-lightbox-thumb\" width=\"824\" data-original=\"https://pic3.zhimg.com/v2-9b8fb5e5230b83e9e47aa0c74311bf06_r.jpg\"\u003e\u003c/noscript\u003e\u003cimg src=\"data:image/svg+xml;utf8,\u0026lt;svg%20xmlns='http://www.w3.org/2000/svg'%20width='824'%20height='447'\u0026gt;\u0026lt;/svg\u0026gt;\" data-caption=\"\" data-size=\"normal\" data-rawwidth=\"824\" data-rawheight=\"447\" data-default-watermark-src=\"https://pic3.zhimg.com/v2-9b8fb5e5230b83e9e47aa0c74311bf06_b.jpg\" class=\"origin_image zh-lightbox-thumb lazy\" width=\"824\" data-original=\"https://pic3.zhimg.com/v2-9b8fb5e5230b83e9e47aa0c74311bf06_r.jpg\" data-actualsrc=\"https://pic3.zhimg.com/v2-9b8fb5e5230b83e9e47aa0c74311bf06_b.jpg\"\u003e\u003c/figure\u003e\u003cp\u003e如上图可知主体“清华北大数学系”不具有“保送”任意一名或多名高中生的能力，有关具体事宜应该咨询所在高中。\u003c/p\u003e\u003cp\u003e另：个人认为系不具有招收保送生的权力，应该是院和校，才有权力招收保送生。\u003c/p\u003e\u003cp\u003e另注：《普通高等学校招收保送生的规定》的颁发部门，原国家教育委员会，已改名为教育部（Ministry of Education of PRC）。\u003c/p\u003e\u003cp\u003e|\u003c/p\u003e\u003cp\u003e|\u003c/p\u003e\u003cp\u003e|\u003c/p\u003e\u003cp\u003e|\u003c/p\u003e\u003cp\u003e|\u003c/p\u003e\u003cp\u003e|\u003c/p\u003e\u003cp\u003e|\u003c/p\u003e\u003cp\u003e|\u003c/p\u003e\u003cp\u003e|\u003c/p\u003e\u003cp\u003e|\u003c/p\u003e\u003cp\u003eAll I want to say is ,that he who has proved Goldbach conjecture definitely has a better logical mind than me.\u003c/p\u003e","relationship":{"upvoted_followees":[]}},{"id":561937861,"type":"answer","answer_type":"normal","question":{"type":"question","id":306537777,"title":"如果高中生能证明哥德巴赫猜想，会被清华北大数学系保送吗？","question_type":"normal","created":1545408745,"updated_time":1545408745,"url":"https://www.zhihu.com/api/v4/questions/306537777","relationship":{}},"author":{"id":"5c9bdb0d7fb1ff4d273ed5990287ebc0","url_token":"acesix","name":"AceSix","avatar_url":"https://pic4.zhimg.com/da8e974dc_is.jpg","avatar_url_template":"https://pic4.zhimg.com/da8e974dc_{size}.jpg","is_org":false,"type":"people","url":"https://www.zhihu.com/api/v4/people/5c9bdb0d7fb1ff4d273ed5990287ebc0","user_type":"people","headline":"在读小学生","badge":[],"gender":-1,"is_advertiser":false,"is_privacy":false},"url":"https://www.zhihu.com/api/v4/answers/561937861","thumbnail":"","is_collapsed":false,"created_time":1546017248,"updated_time":1546017248,"extras":"","is_copyable":true,"is_normal":true,"voteup_count":0,"content":"\u003cp\u003e如果一个人能在20岁之前证明出哥德巴赫猜想，\u003c/p\u003e\u003cp\u003e那他在15岁之前就能拿到普林斯顿数学博士了。\u003c/p\u003e\u003cp\u003e\u003cbr\u003e\u003c/p\u003e\u003cp\u003e清北?\u003c/p\u003e\u003cp\u003e\u003cbr\u003e\u003c/p\u003e\u003cp\u003e要是有那种天才，不到十五岁就考进清北了吧。\u003c/p\u003e\u003cp\u003e更何况有许多天赋没那么恐怖的人，十四五岁也都拿到录取通知书了。\u003c/p\u003e\u003cp\u003e简单表态，我完全否认这个问题的价值，和题主证明成功的可能性。\u003c/p\u003e\u003cp\u003e\u003c/p\u003e","relationship":{"upvoted_followees":[]}},{"id":561921609,"type":"answer","answer_type":"normal","question":{"type":"question","id":306537777,"title":"如果高中生能证明哥德巴赫猜想，会被清华北大数学系保送吗？","question_type":"normal","created":1545408745,"updated_time":1545408745,"url":"https://www.zhihu.com/api/v4/questions/306537777","relationship":{}},"author":{"id":"05a192c0a09a63605357443fb25bbac6","url_token":"a-ke-rui-mu","name":"Fingal Yu","avatar_url":"https://pic1.zhimg.com/v2-e03c3ef11bbb9ec23eea682506b82505_is.jpg","avatar_url_template":"https://pic1.zhimg.com/v2-e03c3ef11bbb9ec23eea682506b82505_{size}.jpg","is_org":false,"type":"people","url":"https://www.zhihu.com/api/v4/people/05a192c0a09a63605357443fb25bbac6","user_type":"people","headline":"一心只想搞生科的垃圾程序猿","badge":[],"gender":1,"is_advertiser":false,"is_privacy":false},"url":"https://www.zhihu.com/api/v4/answers/561921609","thumbnail":"","is_collapsed":false,"created_time":1546014945,"updated_time":1546014945,"extras":"","is_copyable":true,"is_normal":true,"voteup_count":0,"content":"\u003cp\u003e你为什么不想想拿诺奖这种靠谱一点的方法那   \u003c/p\u003e","relationship":{"upvoted_followees":[]}},{"id":561912094,"type":"answer","answer_type":"normal","question":{"type":"question","id":306537777,"title":"如果高中生能证明哥德巴赫猜想，会被清华北大数学系保送吗？","question_type":"normal","created":1545408745,"updated_time":1545408745,"url":"https://www.zhihu.com/api/v4/questions/306537777","relationship":{}},"author":{"id":"393ba6d55fd15e4d7f55b550f54590c0","url_token":"chu-xin-zhen-12","name":"wuer123","avatar_url":"https://pic4.zhimg.com/da8e974dc_is.jpg","avatar_url_template":"https://pic4.zhimg.com/da8e974dc_{size}.jpg","is_org":false,"type":"people","url":"https://www.zhihu.com/api/v4/people/393ba6d55fd15e4d7f55b550f54590c0","user_type":"people","headline":"wuer123","badge":[],"gender":-1,"is_advertiser":false,"is_privacy":false},"url":"https://www.zhihu.com/api/v4/answers/561912094","thumbnail":"","is_collapsed":false,"created_time":1546013797,"updated_time":1546013797,"extras":"","is_copyable":true,"is_normal":true,"voteup_count":0,"content":"\u003cp\u003e都能证出哥德巴赫猜想了，还要上北大？你见过超人开奥迪？\u003c/p\u003e","relationship":{"upvoted_followees":[]}},{"id":561909913,"type":"answer","answer_type":"normal","question":{"type":"question","id":306537777,"title":"如果高中生能证明哥德巴赫猜想，会被清华北大数学系保送吗？","question_type":"normal","created":1545408745,"updated_time":1545408745,"url":"https://www.zhihu.com/api/v4/questions/306537777","relationship":{}},"author":{"id":"dc5a21cefc78484eea6828d1417db884","url_token":"","name":"知乎用户","avatar_url":"https://pic4.zhimg.com/da8e974dc_is.jpg","avatar_url_template":"https://pic4.zhimg.com/da8e974dc_{size}.jpg","is_org":false,"type":"people","url":"https://www.zhihu.com/api/v4/people/0","user_type":"people","headline":"","badge":[],"gender":1,"is_advertiser":false,"is_privacy":true},"url":"https://www.zhihu.com/api/v4/answers/561909913","thumbnail":"","is_collapsed":false,"created_time":1546013534,"updated_time":1546013534,"extras":"","is_copyable":true,"is_normal":true,"voteup_count":0,"content":"\u003cp\u003e题主还差两天，可千万别有什么闪失啊\u003c/p\u003e","relationship":{"upvoted_followees":[]}},{"id":561908521,"type":"answer","answer_type":"normal","question":{"type":"question","id":306537777,"title":"如果高中生能证明哥德巴赫猜想，会被清华北大数学系保送吗？","question_type":"normal","created":1545408745,"updated_time":1545408745,"url":"https://www.zhihu.com/api/v4/questions/306537777","relationship":{}},"author":{"id":"e3e4be48690a89a4069cbee544ae0164","url_token":"ju-mu-3","name":"巨木","avatar_url":"https://pic1.zhimg.com/v2-ebd085eef3ba427f5b490bb26ef97104_is.jpg","avatar_url_template":"https://pic1.zhimg.com/v2-ebd085eef3ba427f5b490bb26ef97104_{size}.jpg","is_org":false,"type":"people","url":"https://www.zhihu.com/api/v4/people/e3e4be48690a89a4069cbee544ae0164","user_type":"people","headline":"","badge":[],"gender":-1,"is_advertiser":false,"is_privacy":false},"url":"https://www.zhihu.com/api/v4/answers/561908521","thumbnail":"","is_collapsed":false,"created_time":1546013356,"updated_time":1546013356,"extras":"","is_copyable":true,"is_normal":true,"voteup_count":0,"content":"\u003cp\u003e如果你能证明哥德巴赫猜想那么保送什么清华北大数学系系对你有意义吗？\u003c/p\u003e","relationship":{"upvoted_followees":[]}},{"id":561902552,"type":"answer","answer_type":"normal","question":{"type":"question","id":306537777,"title":"如果高中生能证明哥德巴赫猜想，会被清华北大数学系保送吗？","question_type":"normal","created":1545408745,"updated_time":1545408745,"url":"https://www.zhihu.com/api/v4/questions/306537777","relationship":{}},"author":{"id":"ddfb3a29fa3d68447d3a75f9a820f14d","url_token":"you-yong-de-yu-0","name":"游泳的鱼0","avatar_url":"https://pic4.zhimg.com/da8e974dc_is.jpg","avatar_url_template":"https://pic4.zhimg.com/da8e974dc_{size}.jpg","is_org":false,"type":"people","url":"https://www.zhihu.com/api/v4/people/ddfb3a29fa3d68447d3a75f9a820f14d","user_type":"people","headline":"长春的一名普通大学生","badge":[],"gender":-1,"is_advertiser":false,"is_privacy":false},"url":"https://www.zhihu.com/api/v4/answers/561902552","thumbnail":"","is_collapsed":false,"created_time":1546012674,"updated_time":1546012674,"extras":"","is_copyable":true,"is_normal":true,"voteup_count":0,"content":"\u003cp\u003e你想证明自己拳击打的好，不用去秒杀泰森\u003c/p\u003e","relationship":{"upvoted_followees":[]}},{"id":561881518,"type":"answer","answer_type":"normal","question":{"type":"question","id":306537777,"title":"如果高中生能证明哥德巴赫猜想，会被清华北大数学系保送吗？","question_type":"normal","created":1545408745,"updated_time":1545408745,"url":"https://www.zhihu.com/api/v4/questions/306537777","relationship":{}},"author":{"id":"bd501c4b31849e9e4cf1143a34852787","url_token":"qing-fu-3-61","name":"轻浮","avatar_url":"https://pic3.zhimg.com/v2-dbf7311a71b2548bc7621dc895323893_is.jpg","avatar_url_template":"https://pic3.zhimg.com/v2-dbf7311a71b2548bc7621dc895323893_{size}.jpg","is_org":false,"type":"people","url":"https://www.zhihu.com/api/v4/people/bd501c4b31849e9e4cf1143a34852787","user_type":"people","headline":"","badge":[],"gender":-1,"is_advertiser":false,"is_privacy":false},"url":"https://www.zhihu.com/api/v4/answers/561881518","thumbnail":"","is_collapsed":false,"created_time":1546010530,"updated_time":1546010530,"extras":"","is_copyable":true,"is_normal":true,"voteup_count":0,"content":"\u003cp\u003e达克效应了解一下\u003c/p\u003e","relationship":{"upvoted_followees":[]}},{"id":561853490,"type":"answer","answer_type":"normal","question":{"type":"question","id":306537777,"title":"如果高中生能证明哥德巴赫猜想，会被清华北大数学系保送吗？","question_type":"normal","created":1545408745,"updated_time":1545408745,"url":"https://www.zhihu.com/api/v4/questions/306537777","relationship":{}},"author":{"id":"0","url_token":"","name":"匿名用户","avatar_url":"https://pic1.zhimg.com/aadd7b895_is.jpg","avatar_url_template":"https://pic1.zhimg.com/aadd7b895_{size}.jpg","is_org":false,"type":"people","url":"https://www.zhihu.com/api/v4/people/0","user_type":"people","headline":"","badge":[],"gender":1,"is_advertiser":false,"follower_count":0,"is_following":false,"is_followed":false,"is_celebrity":false,"is_blocking":false,"is_blocked":false,"is_privacy":false},"url":"https://www.zhihu.com/api/v4/answers/561853490","thumbnail":"","is_collapsed":false,"created_time":1546007858,"updated_time":1546008248,"extras":"","is_copyable":true,"is_normal":true,"voteup_count":0,"content":"\u003cp\u003e如果高中生能证明哥德巴赫猜想，还保送清华北大数学系干嘛？\u003c/p\u003e\u003cp\u003e\u003cbr\u003e\u003c/p\u003e\u003cp\u003e那里根本没有研究数论的老师能教你，你去上班还差不多\u003c/p\u003e","relationship":{"upvoted_followees":[]}},{"id":561841861,"type":"answer","answer_type":"normal","question":{"type":"question","id":306537777,"title":"如果高中生能证明哥德巴赫猜想，会被清华北大数学系保送吗？","question_type":"normal","created":1545408745,"updated_time":1545408745,"url":"https://www.zhihu.com/api/v4/questions/306537777","relationship":{}},"author":{"id":"35c0ca52c8e67002c64d072135207986","url_token":"yezi650","name":"叶子","avatar_url":"https://pic3.zhimg.com/v2-55c8a3b2c27e5f3cef4d2d50f313b1d7_is.jpg","avatar_url_template":"https://pic3.zhimg.com/v2-55c8a3b2c27e5f3cef4d2d50f313b1d7_{size}.jpg","is_org":false,"type":"people","url":"https://www.zhihu.com/api/v4/people/35c0ca52c8e67002c64d072135207986","user_type":"people","headline":"游戏，科幻，科技，人生","badge":[],"gender":1,"is_advertiser":false,"is_privacy":false},"url":"https://www.zhihu.com/api/v4/answers/561841861","thumbnail":"","is_collapsed":false,"created_time":1546006759,"updated_time":1546006759,"extras":"","is_copyable":true,"is_normal":true,"voteup_count":0,"content":"\u003cp\u003e就喜欢你这么厉s害b的人,大家都会难g过x。\u003c/p\u003e","relationship":{"upvoted_followees":[]}},{"id":561832040,"type":"answer","answer_type":"normal","question":{"type":"question","id":306537777,"title":"如果高中生能证明哥德巴赫猜想，会被清华北大数学系保送吗？","question_type":"normal","created":1545408745,"updated_time":1545408745,"url":"https://www.zhihu.com/api/v4/questions/306537777","relationship":{}},"author":{"id":"e122e270883c5952f155c172f0931918","url_token":"ghmbd","name":"ghmbd","avatar_url":"https://pic3.zhimg.com/v2-6a718774544b639fa445f4fb6e7447aa_is.jpg","avatar_url_template":"https://pic3.zhimg.com/v2-6a718774544b639fa445f4fb6e7447aa_{size}.jpg","is_org":false,"type":"people","url":"https://www.zhihu.com/api/v4/people/e122e270883c5952f155c172f0931918","user_type":"people","headline":"数学","badge":[],"gender":-1,"is_advertiser":false,"is_privacy":false},"url":"https://www.zhihu.com/api/v4/answers/561832040","thumbnail":"","is_collapsed":false,"created_time":1546005760,"updated_time":1546005760,"extras":"","is_copyable":true,"is_normal":true,"voteup_count":0,"content":"题主加油，等你1.1证出来后，我相信你一定可以获得诺贝尔数学奖！","relationship":{"upvoted_followees":[]}},{"id":561830816,"type":"answer","answer_type":"normal","question":{"type":"question","id":306537777,"title":"如果高中生能证明哥德巴赫猜想，会被清华北大数学系保送吗？","question_type":"normal","created":1545408745,"updated_time":1545408745,"url":"https://www.zhihu.com/api/v4/questions/306537777","relationship":{}},"author":{"id":"0","url_token":"","name":"匿名用户","avatar_url":"https://pic1.zhimg.com/aadd7b895_is.jpg","avatar_url_template":"https://pic1.zhimg.com/aadd7b895_{size}.jpg","is_org":false,"type":"people","url":"https://www.zhihu.com/api/v4/people/0","user_type":"people","headline":"","badge":[],"gender":1,"is_advertiser":false,"follower_count":0,"is_following":false,"is_followed":false,"is_celebrity":false,"is_blocking":false,"is_blocked":false,"is_privacy":false},"url":"https://www.zhihu.com/api/v4/answers/561830816","thumbnail":"","is_collapsed":false,"created_time":1546005635,"updated_time":1546005635,"extras":"","is_copyable":true,"is_normal":true,"voteup_count":0,"content":"\u003cp\u003e我有一高中同学，从初中开始热衷于推导各种数学公式，后来他去了国科大……\u003c/p\u003e\u003cp\u003e当然，他人是非常聪明的，脑子比我好使。\u003c/p\u003e","relationship":{"upvoted_followees":[]}},{"id":561821850,"type":"answer","answer_type":"normal","question":{"type":"question","id":306537777,"title":"如果高中生能证明哥德巴赫猜想，会被清华北大数学系保送吗？","question_type":"normal","created":1545408745,"updated_time":1545408745,"url":"https://www.zhihu.com/api/v4/questions/306537777","relationship":{}},"author":{"id":"33460d053880183bf16689a610110bdb","url_token":"li-yu-37-85","name":"黎雨","avatar_url":"https://pic4.zhimg.com/da8e974dc_is.jpg","avatar_url_template":"https://pic4.zhimg.com/da8e974dc_{size}.jpg","is_org":false,"type":"people","url":"https://www.zhihu.com/api/v4/people/33460d053880183bf16689a610110bdb","user_type":"people","headline":"教师","badge":[],"gender":-1,"is_advertiser":false,"is_privacy":false},"url":"https://www.zhihu.com/api/v4/answers/561821850","thumbnail":"","is_collapsed":false,"created_time":1546004711,"updated_time":1546032427,"extras":"","is_copyable":true,"is_normal":true,"voteup_count":0,"content":"\u003cp\u003e嗯\u003c/p\u003e","relationship":{"upvoted_followees":[]}},{"id":561821228,"type":"answer","answer_type":"normal","question":{"type":"question","id":306537777,"title":"如果高中生能证明哥德巴赫猜想，会被清华北大数学系保送吗？","question_type":"normal","created":1545408745,"updated_time":1545408745,"url":"https://www.zhihu.com/api/v4/questions/306537777","relationship":{}},"author":{"id":"00736df2a77c833b68f47895125cea83","url_token":"brlangman","name":"别惹浪漫","avatar_url":"https://pic1.zhimg.com/v2-64b850503d9a16ccf649906678c4a77a_is.jpg","avatar_url_template":"https://pic1.zhimg.com/v2-64b850503d9a16ccf649906678c4a77a_{size}.jpg","is_org":false,"type":"people","url":"https://www.zhihu.com/api/v4/people/00736df2a77c833b68f47895125cea83","user_type":"people","headline":"如真如假如可分身饰演自己","badge":[],"gender":1,"is_advertiser":false,"is_privacy":false},"url":"https://www.zhihu.com/api/v4/answers/561821228","thumbnail":"","is_collapsed":false,"created_time":1546004636,"updated_time":1546004702,"extras":"","is_copyable":true,"is_normal":true,"voteup_count":0,"content":"\u003cp\u003e你可以，我也可以作为历史见证者\u003c/p\u003e","relationship":{"upvoted_followees":[]}},{"id":561819194,"type":"answer","answer_type":"normal","question":{"type":"question","id":306537777,"title":"如果高中生能证明哥德巴赫猜想，会被清华北大数学系保送吗？","question_type":"normal","created":1545408745,"updated_time":1545408745,"url":"https://www.zhihu.com/api/v4/questions/306537777","relationship":{}},"author":{"id":"2a3f17e2b57945eb72cf01aab26d620f","url_token":"hui-hui-667","name":"灰灰667","avatar_url":"https://pic4.zhimg.com/v2-1c13f8a23d694543e0b58de81d5ab4b5_is.jpg","avatar_url_template":"https://pic4.zhimg.com/v2-1c13f8a23d694543e0b58de81d5ab4b5_{size}.jpg","is_org":false,"type":"people","url":"https://www.zhihu.com/api/v4/people/2a3f17e2b57945eb72cf01aab26d620f","user_type":"people","headline":"弱弱的程序猿","badge":[],"gender":1,"is_advertiser":false,"is_privacy":false},"url":"https://www.zhihu.com/api/v4/answers/561819194","thumbnail":"","is_collapsed":false,"created_time":1546004397,"updated_time":1546004397,"extras":"","is_copyable":true,"is_normal":true,"voteup_count":0,"content":"\u003cp\u003e高中生要是能证明哥德巴赫。。。清华北大都归他\u003c/p\u003e","relationship":{"upvoted_followees":[]}}],"paging":{"is_end":false,"is_start":false,"next":"https://www.zhihu.com/api/v4/questions/306537777/answers?include=data%5B%2A%5D.is_normal%2Cvoteup_count%2Ccontent\u0026limit=20\u0026offset=1180\u0026sort_by=default","previous":"https://www.zhihu.com/api/v4/questions/306537777/answers?include=data%5B%2A%5D.is_normal%2Cvoteup_count%2Ccontent\u0026limit=20\u0026offset=1140\u0026sort_by=default","totals":1823}}
